smsearch/__init__.py
smsearch/main.py
smsearch-0.1.4.dist-info/LICENSE.txt
smsearch-0.1.4.dist-info/METADATA
smsearch-0.1.4.dist-info/WHEEL
smsearch-0.1.4.dist-info/entry_points.txt
smsearch-0.1.4.dist-info/top_level.txt
smsearch-0.1.4.dist-info/RECORD
