Metadata-Version: 2.1
Name: smsearch
Version: 0.1.4
Summary: A recursive file searcher with boolean expressions.
Home-page: https://github.com/celalertug/smart-search
Author: Celal Ertug
Author-email: celalertug@gmail.com
Classifier: Programming Language :: Python :: 3
Classifier: License :: OSI Approved :: MIT License
Classifier: Operating System :: OS Independent
Requires-Python: >=3.6
License-File: LICENSE.txt
Requires-Dist: pyparsing
Requires-Dist: colorama
Requires-Dist: pyperclip
